edictreader/__init__.py
edictreader/dict.py
edictreader/dir.py
edictreader/database/JMdict_e
edictreader/database/cedict.txt
edictreader/database/cedict_ts.u8
edictreader/database/edict-pos.txt
edictreader/database/edict2
edictreader-0.2.0.dist-info/DESCRIPTION.rst
edictreader-0.2.0.dist-info/METADATA
edictreader-0.2.0.dist-info/RECORD
edictreader-0.2.0.dist-info/WHEEL
edictreader-0.2.0.dist-info/metadata.json
edictreader-0.2.0.dist-info/top_level.txt
edictreader-0.2.0.dist-info/zip-safe
