Metadata-Version: 2.0
Name: edictreader
Version: 0.2.0
Summary: EDICT2, JMdict and CEDICT reader and searcher in dictionary format
Home-page: https://github.com/patarapolw/edictreader
Author: Pacharapol Withayasakpunt
Author-email: patarapolw@gmail.com
License: UNKNOWN
Keywords: EDICT,JMdict,CEDICT
Platform: UNKNOWN
Requires-Python: >=2.7
Requires-Dist: lxml
Requires-Dist: xmltodict
